<users>

    <user>
        <id>1</id>
        <firstName>John</firstName>
        <lastName>Smith</lastName>
        <role>CUSTOMER</role>
        <email>john@gmail.com</email>
        <phone>123456789</phone>
        <createdAt>2026-04-15</createdAt>
    </user>

    <user>
        <id>2</id>
        <firstName>Anna</firstName>
        <lastName>Brown</lastName>
        <role>CUSTOMER</role>
        <email>anna@gmail.com</email>
        <phone>987654321</phone>
        <createdAt>2026-04-15</createdAt>
    </user>

    <user>
        <id>3</id>
        <firstName>Jack</firstName>
        <lastName>Johnson</lastName>
        <role>CUSTOMER</role>
        <email>jack@gmail.com</email>
        <phone>758493091</phone>
        <createdAt>2026-04-15</createdAt>
    </user>

    <user>
        <id>4</id>
        <firstName>Tom</firstName>
        <lastName>Brown</lastName>
        <role>CUSTOMER</role>
        <email>tom@gmail.com</email>
        <phone>987654334</phone>
        <createdAt>2026-04-15</createdAt>
    </user>

    <user>
        <id>5</id>
        <firstName>Petter</firstName>
        <lastName>Solberg</lastName>
        <role>CUSTOMER</role>
        <email>petter@gmail.com</email>
        <phone>9849154321</phone>
        <createdAt>2026-04-15</createdAt>
    </user>

    <user>
        <id>6</id>
        <firstName>Mike</firstName>
        <lastName>Johnson</lastName>
        <role>COURIER</role>
        <email>mike@gmail.com</email>
        <phone>999999109</phone>
        <vehicleType>BIKE</vehicleType>
        <status>AVAILABLE</status>
        <createdAt>2026-04-15</createdAt>
    </user>

    <user>
        <id>7</id>
        <firstName>Sam</firstName>
        <lastName>Smith</lastName>
        <role>COURIER</role>
        <email>sam@gmail.com</email>
        <phone>830549109</phone>
        <vehicleType>Car</vehicleType>
        <status>AVAILABLE</status>
        <createdAt>2026-04-15</createdAt>
    </user>

</users>